dsub/__init__.py
dsub/_dsub_version.py
dsub/commands/__init__.py
dsub/commands/ddel.py
dsub/commands/dstat.py
dsub/commands/dsub.py
dsub/lib/__init__.py
dsub/lib/dsub_errors.py
dsub/lib/dsub_util.py
dsub/lib/job_model.py
dsub/lib/output_formatter.py
dsub/lib/param_util.py
dsub/lib/providers_util.py
dsub/lib/resources.py
dsub/lib/retry_util.py
dsub/providers/__init__.py
dsub/providers/base.py
dsub/providers/batch_dummy.py
dsub/providers/google_base.py
dsub/providers/google_batch.py
dsub/providers/google_batch_operations.py
dsub/providers/google_cls_v2.py
dsub/providers/google_custom_machine.py
dsub/providers/google_utils.py
dsub/providers/google_v2_base.py
dsub/providers/google_v2_operations.py
dsub/providers/google_v2_pipelines.py
dsub/providers/google_v2_versions.py
dsub/providers/local.py
dsub/providers/provider_base.py
dsub/providers/stub.py
dsub/providers/test_fails.py
dsub/providers/local/runner.sh
dsub-0.5.2.dist-info/licenses/LICENSE
test/__init__.py
test/integration/__init__.py
test/integration/e2e_after.py
test/integration/e2e_after_fail.py
test/integration/e2e_env_list.py
test/integration/e2e_io_tasks.py
test/integration/e2e_python_api.py
test/integration/get_data_value.py
test/integration/script_python.py
test/integration/test_setup.py
test/integration/test_setup_e2e.py
test/integration/test_util.py
test/unit/__init__.py
test/unit/batch_client_test.py
test/unit/batch_handling_test.py
test/unit/custom_machine_test.py
test/unit/dstat_test.py
test/unit/dsub_test.py
test/unit/dsub_util_test.py
test/unit/fake_time.py
test/unit/fake_time_test.py
test/unit/gpu_test.py
test/unit/job_model_test.py
test/unit/local_provider_test.py
test/unit/logging_uri_test.py
test/unit/param_util_test.py
test/unit/retrying_test.py
test/unit/rfc3339_test.py
test/unit/stub_provider_test.py
test/unit/wait_and_retry_test.py
dsub-0.5.2.dist-info/METADATA
dsub-0.5.2.dist-info/WHEEL
dsub-0.5.2.dist-info/entry_points.txt
dsub-0.5.2.dist-info/top_level.txt
dsub-0.5.2.dist-info/RECORD
