Metadata-Version: 2.4
Name: dsub
Version: 0.5.2
Summary: A command-line tool that makes it easy to submit and run batch scripts in the cloud
Home-page: https://github.com/DataBiosphere/dsub
Author: Verily
License: Apache
Keywords: cloud bioinformatics
Classifier: Development Status :: 4 - Beta
Classifier: Intended Audience :: Developers
Classifier: Topic :: Scientific/Engineering :: Bio-Informatics
Classifier: Topic :: Scientific/Engineering :: Information Analysis
Classifier: Topic :: System :: Distributed Computing
Classifier: License :: OSI Approved :: Apache Software License
Classifier: Programming Language :: Python :: 3.7
Classifier: Programming Language :: Python :: 3.8
Classifier: Programming Language :: Python :: 3.9
Classifier: Programming Language :: Python :: 3.10
Requires-Python: >=3.7
License-File: LICENSE
Requires-Dist: google-api-python-client<=2.181.0,>=2.47.0
Requires-Dist: google-auth<=2.40.3,>=2.6.6
Requires-Dist: google-cloud-batch>=0.17.36
Requires-Dist: python-dateutil<=2.9.0
Requires-Dist: pytz<=2025.2
Requires-Dist: pyyaml<=6.0.1
Requires-Dist: tenacity<=8.2.3
Requires-Dist: tabulate<=0.9.0
Requires-Dist: funcsigs==1.0.2
Requires-Dist: google-api-core<=2.25.1,>=2.7.3
Requires-Dist: google-auth-httplib2<=0.2.0
Requires-Dist: httplib2<=0.22.0
Requires-Dist: protobuf<=6.32.0,>=3.19.0
Requires-Dist: pyasn1<=0.6.0
Requires-Dist: pyasn1-modules<=0.4.0
Requires-Dist: rsa<=4.9
Requires-Dist: uritemplate<=4.1.1
Requires-Dist: parameterized<=0.9.0
Requires-Dist: mock<=5.1.0
Dynamic: author
Dynamic: classifier
Dynamic: description
Dynamic: description-content-type
Dynamic: home-page
Dynamic: keywords
Dynamic: license
Dynamic: license-file
Dynamic: requires-dist
Dynamic: requires-python
Dynamic: summary
